invenio_access/__init__.py
invenio_access/admin.py
invenio_access/cli.py
invenio_access/config.py
invenio_access/ext.py
invenio_access/factory.py
invenio_access/loaders.py
invenio_access/models.py
invenio_access/permissions.py
invenio_access/proxies.py
invenio_access/utils.py
invenio_access/alembic/04480be1593e_add_actionsystemroles.py
invenio_access/alembic/2069a982633b_add_on_delete_cascade_constraint.py
invenio_access/alembic/2f63be7b7572_create_access_tables.py
invenio_access/alembic/67ba0de65fbb_create_access_branch.py
invenio_access/alembic/842a62b56e60_change_fk_accountsrole_to_string_downgrade.py
invenio_access/alembic/dbe499bfda43_prevent_null_in_actionusers_for_.py
invenio_access/alembic/f9843093f686_change_fk_accountsrole_to_string_upgrade.py
invenio_access/translations/messages.pot
invenio_access/translations/ar/LC_MESSAGES/messages.mo
invenio_access/translations/ar/LC_MESSAGES/messages.po
invenio_access/translations/bg/LC_MESSAGES/messages.mo
invenio_access/translations/bg/LC_MESSAGES/messages.po
invenio_access/translations/ca/LC_MESSAGES/messages.mo
invenio_access/translations/ca/LC_MESSAGES/messages.po
invenio_access/translations/cs/LC_MESSAGES/messages.mo
invenio_access/translations/cs/LC_MESSAGES/messages.po
invenio_access/translations/da/LC_MESSAGES/messages.mo
invenio_access/translations/da/LC_MESSAGES/messages.po
invenio_access/translations/de/LC_MESSAGES/messages.mo
invenio_access/translations/de/LC_MESSAGES/messages.po
invenio_access/translations/el/LC_MESSAGES/messages.mo
invenio_access/translations/el/LC_MESSAGES/messages.po
invenio_access/translations/es/LC_MESSAGES/messages.mo
invenio_access/translations/es/LC_MESSAGES/messages.po
invenio_access/translations/et/LC_MESSAGES/messages.mo
invenio_access/translations/et/LC_MESSAGES/messages.po
invenio_access/translations/fa/LC_MESSAGES/messages.mo
invenio_access/translations/fa/LC_MESSAGES/messages.po
invenio_access/translations/fi/LC_MESSAGES/messages.mo
invenio_access-4.2.1.dist-info/licenses/AUTHORS.rst
invenio_access-4.2.1.dist-info/licenses/LICENSE
invenio_access-4.2.1.dist-info/METADATA
invenio_access-4.2.1.dist-info/WHEEL
invenio_access-4.2.1.dist-info/entry_points.txt
invenio_access-4.2.1.dist-info/top_level.txt
invenio_access-4.2.1.dist-info/RECORD
