Metadata-Version: 2.4
Name: invenio-access
Version: 4.2.1
Summary: Invenio module for common role based access control.
Home-page: https://github.com/inveniosoftware/invenio-access
Author: CERN
Author-email: info@inveniosoftware.org
License: MIT
Keywords: invenio access
Platform: any
Classifier: Development Status :: 5 - Production/Stable
Requires-Python: >=3.7
License-File: LICENSE
License-File: AUTHORS.rst
Requires-Dist: invenio-accounts<7.0.0,>=6.0.0
Requires-Dist: invenio-base<3.0.0,>=2.3.0
Requires-Dist: invenio-i18n<4.0.0,>=3.0.0
Provides-Extra: tests
Requires-Dist: cachelib>=0.1; extra == "tests"
Requires-Dist: invenio-db[mysql,postgresql]<3.0.0,>=2.0.0; extra == "tests"
Requires-Dist: pytest-black-ng>=0.4.0; extra == "tests"
Requires-Dist: pytest-invenio<4.0.0,>=3.0.0; extra == "tests"
Requires-Dist: redis>=2.10.5; extra == "tests"
Requires-Dist: sphinx>=4.5; extra == "tests"
Provides-Extra: admin
Requires-Dist: invenio-admin<2.0.0,>=1.2.0; extra == "admin"
Provides-Extra: postgresql
Provides-Extra: mysql
Provides-Extra: sqlite
Dynamic: license-file
